opencensus/__init__.py
opencensus/ext/__init__.py
opencensus/ext/fastapi/__init__.py
opencensus/ext/fastapi/fastapi_middleware.py
opencensus_ext_fastapi-0.1.0.dist-info/METADATA
opencensus_ext_fastapi-0.1.0.dist-info/WHEEL
opencensus_ext_fastapi-0.1.0.dist-info/namespace_packages.txt
opencensus_ext_fastapi-0.1.0.dist-info/top_level.txt
opencensus_ext_fastapi-0.1.0.dist-info/RECORD
